remla_preprocess/__init__.py
remla_preprocess/pre_processing.py
remla_preprocess-3.dist-info/LICENSE
remla_preprocess-3.dist-info/METADATA
remla_preprocess-3.dist-info/WHEEL
remla_preprocess-3.dist-info/RECORD
